utils_rag/EnhancedLocalEmbeddings.py
utils_rag/__init__.py
utils_rag-1.0.6.dist-info/LICENSE
utils_rag-1.0.6.dist-info/METADATA
utils_rag-1.0.6.dist-info/WHEEL
utils_rag-1.0.6.dist-info/top_level.txt
utils_rag-1.0.6.dist-info/RECORD
