Metadata-Version: 2.1
Name: utils_rag
Version: 1.0.6
Summary: Here is an enhanced version of the LocalEmbeddings class that provides similar functionality to the OpenAI embedding model and includes more features and detailed comments in English and Chinese
Home-page: https://github.com/Fangzhou-Code/Utils
Author: FangZhou
Author-email: noah183225@gamil.com
Classifier: Programming Language :: Python :: 3
Classifier: License :: OSI Approved :: MIT License
Classifier: Operating System :: OS Independent
Requires-Python: >=3.8
License-File: LICENSE
